sqlviewer/__init__.py
sqlviewer/connector.py
sqlviewer/render.py
sqlviewer/viewer.py
sqlviewer-0.1.1.dist-info/LICENSE
sqlviewer-0.1.1.dist-info/METADATA
sqlviewer-0.1.1.dist-info/WHEEL
sqlviewer-0.1.1.dist-info/entry_points.txt
sqlviewer-0.1.1.dist-info/top_level.txt
sqlviewer-0.1.1.dist-info/RECORD
