Metadata-Version: 2.1
Name: sqlviewer
Version: 0.1.1
Summary: Basic cli sql viewer for databases - intended to allow for quick sanity checks
Home-page: UNKNOWN
Author: Kieran Bacon
Author-email: kieran.bacon@outlook.com
License: UNKNOWN
Platform: UNKNOWN
Requires-Dist: betterpy
Requires-Dist: psycopg2
